Workbook

Sheet Instrucciones
B2: Plan de pruebas QA — ERP Integrado
B3: App local: http://localhost:5195 · Admin demo: admin@erp.com · Cajero demo: CAJA1
B5: Cómo usarlo | C5: Ve a la hoja 'Casos QA' y sigue los pasos de cada caso. Cambia la columna 'Estado' con la lista desplegable.
B6: Estados | C6: Pendiente = falta probar · En proceso = se está probando / corrigiendo · Listo = pasó la prueba · Falla = no cumplió el resultado esperado.
B7: Si algo falla | C7: Marca 'Falla' y anota en 'Resultado obtenido' qué pasó (mensaje de error, pantalla, captura). Cuando se corrija, pasa a 'En proceso' y luego a 'Listo'.
B8: Colores | C8: La fila de Estado se colorea sola: gris = Pendiente, amarillo = En proceso, verde = Listo, rojo = Falla.
B9: Resumen | C9: La hoja 'Resumen' calcula con fórmulas el avance total y por módulo; no hay que editarla.
B10: Celdas a editar | C10: Estado, Resultado obtenido, Responsable, Fecha y Observaciones (columnas con encabezado azul claro). El resto es la definición del caso.
B11: Ejemplo | C11: Fila de ejemplo: ID QA-001 — Estado 'Listo', Responsable 'María', Fecha 2026-10-29, Resultado obtenido 'Entró al index sin errores'.

Sheet Resumen
B2: Resumen de avance QA
B4: Módulo | C4: Total | D4: Listo | E4: En proceso | F4: Falla | G4: Pendiente | H4: % Listo
B5: Acceso y seguridad | C5: =COUNTIF('Casos QA'!$B$2:$B$70,B5) | D5: =COUNTIFS('Casos QA'!$B$2:$B$70,$B5,'Casos QA'!$H$2:$H$70,"Listo") | E5: =COUNTIFS('Casos QA'!$B$2:$B$70,$B5,'Casos QA'!$H$2:$H$70,"En proceso") | F5: =COUNTIFS('Casos QA'!$B$2:$B$70,$B5,'Casos QA'!$H$2:$H$70,"Falla") | G5: =COUNTIFS('Casos QA'!$B$2:$B$70,$B5,'Casos QA'!$H$2:$H$70,"Pendiente") | H5: =IF(C5=0,0,D5/C5)
B6: Catálogo / Productos | C6: =COUNTIF('Casos QA'!$B$2:$B$70,B6) | D6: =COUNTIFS('Casos QA'!$B$2:$B$70,$B6,'Casos QA'!$H$2:$H$70,"Listo") | E6: =COUNTIFS('Casos QA'!$B$2:$B$70,$B6,'Casos QA'!$H$2:$H$70,"En proceso") | F6: =COUNTIFS('Casos QA'!$B$2:$B$70,$B6,'Casos QA'!$H$2:$H$70,"Falla") | G6: =COUNTIFS('Casos QA'!$B$2:$B$70,$B6,'Casos QA'!$H$2:$H$70,"Pendiente") | H6: =IF(C6=0,0,D6/C6)
B7: Clientes | C7: =COUNTIF('Casos QA'!$B$2:$B$70,B7) | D7: =COUNTIFS('Casos QA'!$B$2:$B$70,$B7,'Casos QA'!$H$2:$H$70,"Listo") | E7: =COUNTIFS('Casos QA'!$B$2:$B$70,$B7,'Casos QA'!$H$2:$H$70,"En proceso") | F7: =COUNTIFS('Casos QA'!$B$2:$B$70,$B7,'Casos QA'!$H$2:$H$70,"Falla") | G7: =COUNTIFS('Casos QA'!$B$2:$B$70,$B7,'Casos QA'!$H$2:$H$70,"Pendiente") | H7: =IF(C7=0,0,D7/C7)
B8: Proveedores | C8: =COUNTIF('Casos QA'!$B$2:$B$70,B8) | D8: =COUNTIFS('Casos QA'!$B$2:$B$70,$B8,'Casos QA'!$H$2:$H$70,"Listo") | E8: =COUNTIFS('Casos QA'!$B$2:$B$70,$B8,'Casos QA'!$H$2:$H$70,"En proceso") | F8: =COUNTIFS('Casos QA'!$B$2:$B$70,$B8,'Casos QA'!$H$2:$H$70,"Falla") | G8: =COUNTIFS('Casos QA'!$B$2:$B$70,$B8,'Casos QA'!$H$2:$H$70,"Pendiente") | H8: =IF(C8=0,0,D8/C8)
B9: Compras | C9: =COUNTIF('Casos QA'!$B$2:$B$70,B9) | D9: =COUNTIFS('Casos QA'!$B$2:$B$70,$B9,'Casos QA'!$H$2:$H$70,"Listo") | E9: =COUNTIFS('Casos QA'!$B$2:$B$70,$B9,'Casos QA'!$H$2:$H$70,"En proceso") | F9: =COUNTIFS('Casos QA'!$B$2:$B$70,$B9,'Casos QA'!$H$2:$H$70,"Falla") | G9: =COUNTIFS('Casos QA'!$B$2:$B$70,$B9,'Casos QA'!$H$2:$H$70,"Pendiente") | H9: =IF(C9=0,0,D9/C9)
B10: Inventario | C10: =COUNTIF('Casos QA'!$B$2:$B$70,B10) | D10: =COUNTIFS('Casos QA'!$B$2:$B$70,$B10,'Casos QA'!$H$2:$H$70,"Listo") | E10: =COUNTIFS('Casos QA'!$B$2:$B$70,$B10,'Casos QA'!$H$2:$H$70,"En proceso") | F10: =COUNTIFS('Casos QA'!$B$2:$B$70,$B10,'Casos QA'!$H$2:$H$70,"Falla") | G10: =COUNTIFS('Casos QA'!$B$2:$B$70,$B10,'Casos QA'!$H$2:$H$70,"Pendiente") | H10: =IF(C10=0,0,D10/C10)
B11: Ventas | C11: =COUNTIF('Casos QA'!$B$2:$B$70,B11) | D11: =COUNTIFS('Casos QA'!$B$2:$B$70,$B11,'Casos QA'!$H$2:$H$70,"Listo") | E11: =COUNTIFS('Casos QA'!$B$2:$B$70,$B11,'Casos QA'!$H$2:$H$70,"En proceso") | F11: =COUNTIFS('Casos QA'!$B$2:$B$70,$B11,'Casos QA'!$H$2:$H$70,"Falla") | G11: =COUNTIFS('Casos QA'!$B$2:$B$70,$B11,'Casos QA'!$H$2:$H$70,"Pendiente") | H11: =IF(C11=0,0,D11/C11)
B12: Cobranzas | C12: =COUNTIF('Casos QA'!$B$2:$B$70,B12) | D12: =COUNTIFS('Casos QA'!$B$2:$B$70,$B12,'Casos QA'!$H$2:$H$70,"Listo") | E12: =COUNTIFS('Casos QA'!$B$2:$B$70,$B12,'Casos QA'!$H$2:$H$70,"En proceso") | F12: =COUNTIFS('Casos QA'!$B$2:$B$70,$B12,'Casos QA'!$H$2:$H$70,"Falla") | G12: =COUNTIFS('Casos QA'!$B$2:$B$70,$B12,'Casos QA'!$H$2:$H$70,"Pendiente") | H12: =IF(C12=0,0,D12/C12)
B13: Contabilidad | C13: =COUNTIF('Casos QA'!$B$2:$B$70,B13) | D13: =COUNTIFS('Casos QA'!$B$2:$B$70,$B13,'Casos QA'!$H$2:$H$70,"Listo") | E13: =COUNTIFS('Casos QA'!$B$2:$B$70,$B13,'Casos QA'!$H$2:$H$70,"En proceso") | F13: =COUNTIFS('Casos QA'!$B$2:$B$70,$B13,'Casos QA'!$H$2:$H$70,"Falla") | G13: =COUNTIFS('Casos QA'!$B$2:$B$70,$B13,'Casos QA'!$H$2:$H$70,"Pendiente") | H13: =IF(C13=0,0,D13/C13)
B14: Integración contable | C14: =COUNTIF('Casos QA'!$B$2:$B$70,B14) | D14: =COUNTIFS('Casos QA'!$B$2:$B$70,$B14,'Casos QA'!$H$2:$H$70,"Listo") | E14: =COUNTIFS('Casos QA'!$B$2:$B$70,$B14,'Casos QA'!$H$2:$H$70,"En proceso") | F14: =COUNTIFS('Casos QA'!$B$2:$B$70,$B14,'Casos QA'!$H$2:$H$70,"Falla") | G14: =COUNTIFS('Casos QA'!$B$2:$B$70,$B14,'Casos QA'!$H$2:$H$70,"Pendiente") | H14: =IF(C14=0,0,D14/C14)
B15: Flujo E2E | C15: =COUNTIF('Casos QA'!$B$2:$B$70,B15) | D15: =COUNTIFS('Casos QA'!$B$2:$B$70,$B15,'Casos QA'!$H$2:$H$70,"Listo") | E15: =COUNTIFS('Casos QA'!$B$2:$B$70,$B15,'Casos QA'!$H$2:$H$70,"En proceso") | F15: =COUNTIFS('Casos QA'!$B$2:$B$70,$B15,'Casos QA'!$H$2:$H$70,"Falla") | G15: =COUNTIFS('Casos QA'!$B$2:$B$70,$B15,'Casos QA'!$H$2:$H$70,"Pendiente") | H15: =IF(C15=0,0,D15/C15)
B16: TOTAL | C16: =SUM(C5:C15) | D16: =SUM(D5:D15) | E16: =SUM(E5:E15) | F16: =SUM(F5:F15) | G16: =SUM(G5:G15) | H16: =IF(C16=0,0,D16/C16)
B18: Los conteos se recalculan solos a partir de la columna Estado de 'Casos QA'.

Sheet Casos QA
A1: ID | B1: Módulo | C1: Pantalla | D1: Caso de prueba | E1: Precondiciones | F1: Pasos | G1: Resultado esperado | H1: Estado | I1: Resultado obtenido | J1: Responsable | K1: Fecha | L1: Observaciones
A2: QA-001 | B2: Acceso y seguridad | C2: login.html | D2: Login con administrador | E2: API en marcha (http://localhost:5195) | F2: 1. Abrir login. 2. Pulsar 'Usar' en Administrador. 3. Ingresar. | G2: Entra a index_erp.html y se ve la navbar con todos los módulos. | H2: Listo | I2: Entró al index sin errores (ejemplo) | J2: María | K2: 46324
A3: QA-002 | B3: Acceso y seguridad | C3: login.html | D3: Login con credenciales inválidas | E3: — | F3: Ingresar usuario válido con contraseña errónea. | G3: Mensaje de error claro; no se crea sesión. | H3: Pendiente
A4: QA-003 | B4: Acceso y seguridad | C4: login.html | D4: Login con cajero | E4: Usuario CAJA1 existe | F4: Ingresar con CAJA1 / CAJA123. | G4: Entra a la pantalla permitida (caja/ventas) con navbar limitada. | H4: Pendiente
A5: QA-004 | B5: Acceso y seguridad | C5: acceso_denegado.html | D5: Cajero no accede a pantallas administrativas | E5: Sesión de cajero | F5: Abrir por URL pantalla_admin_usuarios.html y pantalla_configuracion_integracion.html. | G5: Redirige a acceso_denegado.html; la API responde 403. | H5: Pendiente
A6: QA-005 | B6: Acceso y seguridad | C6: Todas | D6: Expiración de sesión | E6: Sesión iniciada | F6: Borrar/invalidar token y recargar cualquier pantalla. | G6: Vuelve a login.html?motivo=sesion sin errores en consola. | H6: Pendiente
A7: QA-006 | B7: Acceso y seguridad | C7: pantalla_admin_usuarios.html | D7: Crear usuario nuevo | E7: Sesión admin | F7: Crear usuario con rol Cajero; iniciar sesión con él. | G7: Usuario creado y puede ingresar con sus permisos. | H7: Pendiente
A8: QA-007 | B8: Acceso y seguridad | C8: pantalla_admin_usuarios.html | D8: Editar permisos de un rol | E8: Sesión admin | F8: Cambiar permisos de un rol y re-ingresar con un usuario de ese rol. | G8: Los permisos se reflejan en navbar y en la API. | H8: Pendiente
A9: QA-008 | B9: Acceso y seguridad | C9: pantalla_admin_usuarios.html | D9: Desactivar usuario | E9: Usuario de prueba existe | F9: Desactivar usuario e intentar ingresar. | G9: No puede iniciar sesión. | H9: Pendiente
A10: QA-009 | B10: Acceso y seguridad | C10: pantalla_auditoria.html | D10: Registro de auditoría | E10: Se hicieron acciones previas | F10: Abrir auditoría; filtrar por usuario, módulo y fecha. | G10: Lista eventos recientes y los filtros funcionan. | H10: Pendiente
A11: QA-010 | B11: Catálogo / Productos | C11: pantalla_catalogo_productos.html | D11: Listar productos | E11: Hay productos cargados | F11: Abrir la pantalla. | G11: Carga el listado sin errores en consola. | H11: Pendiente
A12: QA-011 | B12: Catálogo / Productos | C12: pantalla_catalogo_productos.html | D12: Crear producto con stock inicial | E12: Sesión admin | F12: Crear producto (código, precio, unidad de medida) con stock inicial > 0. | G12: Producto aparece en el catálogo; stock inicial queda en inventario y Kardex. | H12: Pendiente
A13: QA-012 | B13: Catálogo / Productos | C13: pantalla_catalogo_productos.html | D13: Validar campos obligatorios | E13: — | F13: Intentar guardar sin nombre/código/precio. | G13: Muestra validaciones; no guarda. | H13: Pendiente
A14: QA-013 | B14: Catálogo / Productos | C14: pantalla_catalogo_productos.html | D14: Código de producto duplicado | E14: Producto existente | F14: Crear otro producto con el mismo código. | G14: Rechaza con mensaje claro. | H14: Pendiente
... A70: QA-069 | B70: Flujo E2E | C70: Varias | D70: E2E 4: Navegación completa | E70: Sesión admin | F70: Recorrer todas las opciones de la navbar. | G70: Ninguna pantalla muestra error ni consola con errores rojos. | H70: Pendiente
